{"favorited": false, "lang": "en", "timestamp_ms": "1516388535862", "coordinates": null, "is_quote_status": false, "retweeted": false, "in_reply_to_user_id": null, "smapp_timestamp": "Fri Jan 19 14:02:16 +0000 2018", "entities": {"symbols": [], "user_mentions": [{"indices": [3, 13], "id_str": "38001218", "id": 38001218, "screen_name": "NEDAstaff", "name": "NEDA"}], "hashtags": [{"text": "MeToo", "indices": [122, 128]}], "urls": []}, "user": {"profile_image_url_https": "https://pbs.twimg.com/profile_images/945741006753824768/bJV1g4YN_normal.jpg", "lang": "en", "screen_name": "neeshaarter", "profile_sidebar_fill_color": "FFFFFF", "statuses_count": 5233, "followers_count": 4386, "url": "http://amzn.com/1942762143", "verified": true, "profile_background_image_url": "http://pbs.twimg.com/profile_background_images/378800000165411773/JvhkdUVj.jpeg", "location": "New York, New York", "profile_text_color": "666666", "contributors_enabled": false, "favourites_count": 390, "protected": false, "default_profile_image": false, "profile_background_tile": true, "id_str": "113855028", "id": 113855028, "profile_background_image_url_https": "https://pbs.twimg.com/profile_background_images/378800000165411773/JvhkdUVj.jpeg", "default_profile": false, "profile_banner_url": "https://pbs.twimg.com/profile_banners/113855028/1485814530", "is_translator": false, "listed_count": 50, "profile_use_background_image": true, "notifications": null, "geo_enabled": true, "profile_background_color": "B8B8B8", "translator_type": "none", "profile_image_url": "http://pbs.twimg.com/profile_images/945741006753824768/bJV1g4YN_normal.jpg", "profile_link_color": "A8425E", "friends_count": 253, "description": "Author of the memoir CONTROLLED on #SexualAssault \n\ud83c\udf99 Co-Host of @thesocialweekly Podcast \n\u2712\ufe0f Director of Social Media @dmssocial", "time_zone": "Pacific Time (US & Canada)", "follow_request_sent": null, "name": "Neesha Arter", "following": null, "utc_offset": -28800, "profile_sidebar_border_color": "000000", "created_at": "Sat Feb 13 07:42:36 +0000 2010"}, "in_reply_to_status_id_str": null, "id_str": "954428811977940992", "id": 954428811977940992, "contributors": null, "in_reply_to_screen_name": null, "filter_level": "low", "favorite_count": 0, "retweeted_status": {"favorited": false, "lang": "en", "coordinates": null, "is_quote_status": false, "retweeted": false, "in_reply_to_user_id": null, "extended_tweet": {"full_text": "\"For many years, I felt like I was screaming in a crowded room and no one would even turn their head...the #MeToo movement has given me, and so many others, hope.\" -@neeshaarter #FundMyFearless #WomensMarch \n\nhttps://t.co/XGUdzGuLNx", "entities": {"symbols": [], "user_mentions": [{"indices": [165, 177], "id_str": "113855028", "id": 113855028, "screen_name": "neeshaarter", "name": "Neesha Arter"}], "hashtags": [{"text": "MeToo", "indices": [107, 113]}, {"text": "FundMyFearless", "indices": [178, 193]}, {"text": "WomensMarch", "indices": [194, 206]}], "urls": [{"url": "https://t.co/XGUdzGuLNx", "display_url": "nationaleatingdisorders.org/blog/metoo-mov\u2026", "indices": [209, 232], "expanded_url": "https://www.nationaleatingdisorders.org/blog/metoo-movement-gives-me-hope-world-without-abuse"}]}, "display_text_range": [0, 232]}, "entities": {"symbols": [], "user_mentions": [], "hashtags": [{"text": "MeToo", "indices": [107, 113]}], "urls": [{"url": "https://t.co/VMsgBhl3RC", "display_url": "twitter.com/i/web/status/9\u2026", "indices": [117, 140], "expanded_url": "https://twitter.com/i/web/status/954427280020959233"}]}, "user": {"profile_image_url_https": "https://pbs.twimg.com/profile_images/948937727084564480/ACiB1nRa_normal.jpg", "lang": "en", "screen_name": "NEDAstaff", "profile_sidebar_fill_color": "D4C1B2", "statuses_count": 10826, "followers_count": 35145, "url": "http://www.nationaleatingdisorders.org", "verified": true, "profile_background_image_url": "http://pbs.twimg.com/profile_background_images/489708755227910145/5lGQCsk9.png", "location": "New York, NY", "profile_text_color": "B1C4B8", "contributors_enabled": false, "favourites_count": 6870, "protected": false, "default_profile_image": false, "profile_background_tile": false, "id_str": "38001218", "id": 38001218, "profile_background_image_url_https": "https://pbs.twimg.com/profile_background_images/489708755227910145/5lGQCsk9.png", "default_profile": false, "profile_banner_url": "https://pbs.twimg.com/profile_banners/38001218/1515079269", "is_translator": false, "listed_count": 465, "profile_use_background_image": false, "notifications": null, "geo_enabled": true, "profile_background_color": "94C854", "translator_type": "none", "profile_image_url": "http://pbs.twimg.com/profile_images/948937727084564480/ACiB1nRa_normal.jpg", "profile_link_color": "005DAA", "friends_count": 2825, "description": "NEDA supports individuals & families affected by eating disorders; serves as a catalyst for prevention, cures & access to care. National Helpline: 800.931.2237", "time_zone": "Eastern Time (US & Canada)", "follow_request_sent": null, "name": "NEDA", "following": null, "utc_offset": -18000, "profile_sidebar_border_color": "FFFFFF", "created_at": "Tue May 05 19:44:04 +0000 2009"}, "in_reply_to_status_id_str": null, "id_str": "954427280020959233", "id": 954427280020959233, "contributors": null, "in_reply_to_screen_name": null, "filter_level": "low", "possibly_sensitive": false, "favorite_count": 1, "source": "<a href=\"http://twitter.com\" rel=\"nofollow\">Twitter Web Client</a>", "in_reply_to_user_id_str": null, "quote_count": 0, "retweet_count": 1, "place": null, "truncated": true, "in_reply_to_status_id": null, "text": "\"For many years, I felt like I was screaming in a crowded room and no one would even turn their head...the #MeToo m\u2026 https://t.co/VMsgBhl3RC", "reply_count": 0, "geo": null, "created_at": "Fri Jan 19 18:56:10 +0000 2018"}, "source": "<a href=\"http://twitter.com\" rel=\"nofollow\">Twitter Web Client</a>", "in_reply_to_user_id_str": null, "quote_count": 0, "retweet_count": 0, "place": null, "truncated": false, "in_reply_to_status_id": null, "text": "RT @NEDAstaff: \"For many years, I felt like I was screaming in a crowded room and no one would even turn their head...the #MeToo movement h\u2026", "reply_count": 0, "geo": null, "created_at": "Fri Jan 19 19:02:15 +0000 2018"}