{"geo": null, "in_reply_to_user_id_str": null, "in_reply_to_screen_name": null, "text": "RT @CaliLiliIndies: @ECMcLaughlin @dawnresist n Hard Times \u00a9 #Anthem 4 #Choice #Women #LGBTQ #BlackLivesMatter #STEM #Democracy \ud83c\udfc4\u200d\u2640\ufe0f  https\u2026", "user": {"following": null, "time_zone": "Central Time (US & Canada)", "profile_image_url_https": "https://pbs.twimg.com/profile_images/923019880491831296/w07NxxIp_normal.jpg", "contributors_enabled": false, "profile_link_color": "E81C4F", "profile_sidebar_fill_color": "7AC3EE", "favourites_count": 141076, "default_profile": false, "description": "#TheResistance\u2744\ufe0f#BeTheChange\ud83c\udf38#BreakTheSilence\u2744\ufe0f#HumanRights\ud83c\udf38#StrongerTogether\u2744\ufe0f#MeToo\ud83c\udf38#KindnessMatters\u2744\ufe0f@audreyandirene\ud83c\udf38", "verified": false, "friends_count": 20528, "is_translator": false, "id_str": "1952510090", "profile_text_color": "3D1957", "created_at": "Thu Oct 10 20:00:12 +0000 2013", "followers_count": 19139, "notifications": null, "profile_banner_url": "https://pbs.twimg.com/profile_banners/1952510090/1509052704", "profile_image_url": "http://pbs.twimg.com/profile_images/923019880491831296/w07NxxIp_normal.jpg", "profile_background_image_url": "http://pbs.twimg.com/profile_background_images/476788331108249600/tkk9_142.jpeg", "protected": false, "geo_enabled": false, "profile_sidebar_border_color": "65B0DA", "translator_type": "none", "id": 1952510090, "statuses_count": 124991, "name": "Dawn \ud83d\udc9c#Resist \ud83c\udf0a\ud83c\udf0a2018", "location": "Report Porn Block Trolls & MLM", "utc_offset": -21600, "profile_background_color": "01519A", "url": "https://audrey-irene.myshopify.com", "screen_name": "dawnresist", "profile_use_background_image": true, "follow_request_sent": null, "default_profile_image": false, "listed_count": 316, "profile_background_tile": true, "lang": "en", "profile_background_image_url_https": "https://pbs.twimg.com/profile_background_images/476788331108249600/tkk9_142.jpeg"}, "quoted_status_id_str": "882138869986086913", "id": 954544436255608837, "place": null, "id_str": "954544436255608837", "is_quote_status": true, "truncated": false, "created_at": "Sat Jan 20 02:41:42 +0000 2018", "source": "<a href=\"http://twitter.com/download/iphone\" rel=\"nofollow\">Twitter for iPhone</a>", "filter_level": "low", "retweet_count": 0, "favorite_count": 0, "smapp_timestamp": "Fri Jan 19 21:41:43 +0000 2018", "retweeted_status": {"geo": null, "in_reply_to_user_id_str": "335060282", "in_reply_to_screen_name": "ECMcLaughlin", "quoted_status_id_str": "882138869986086913", "user": {"following": null, "time_zone": "Pacific Time (US & Canada)", "profile_image_url_https": "https://pbs.twimg.com/profile_images/2297895474/0w7offhzcf53vt5yk3w3_normal.jpeg", "contributors_enabled": false, "profile_link_color": "E22FEB", "profile_sidebar_fill_color": "F6FFD1", "favourites_count": 27403, "default_profile": false, "description": "\u00a9CaliLiliIndies\u2122\nPiXWordsMusicInMotion\u2122 feMt0\u2122studi0* CuttingEdgeOfThePacific\u2122 #ActorDirector #SingerSongwriter  https://t.co/89A0WTyf6U IslandChildWild\u2122\ud83c\udfc4", "verified": false, "friends_count": 3992, "is_translator": false, "id_str": "594100783", "profile_text_color": "333333", "created_at": "Tue May 29 22:44:21 +0000 2012", "followers_count": 4885, "notifications": null, "profile_banner_url": "https://pbs.twimg.com/profile_banners/594100783/1401331749", "profile_image_url": "http://pbs.twimg.com/profile_images/2297895474/0w7offhzcf53vt5yk3w3_normal.jpeg", "profile_background_image_url": "http://pbs.twimg.com/profile_background_images/378800000113803018/be332da092a8abf8661fe657f6427d2c.jpeg", "protected": false, "geo_enabled": false, "profile_sidebar_border_color": "FFFFFF", "translator_type": "none", "id": 594100783, "statuses_count": 107646, "name": "CaliLili\u2122\ud83c\udf2c\ufe0f\ud83c\udf0a\ud83d\udc2c\ud83c\udf0a \ud83c\udf08\ud83c\udfc4\u200d\u2640\ufe0f\ud83c\udff3\ufe0f\u200d\ud83c\udf08\ud83d\udc9e\ud83d\ude0e\ud83e\udd19\ud83d\udd4a\ufe0f\ud83c\udf0d", "location": "TheCaliLiliIndies\u2122VenusBeach\u2122", "utc_offset": -28800, "profile_background_color": "1A1B1F", "url": "https://www.youtube.com/watch?v=ybFeysEAHtk&feature=youtu.be", "screen_name": "CaliLiliIndies", "profile_use_background_image": true, "follow_request_sent": null, "default_profile_image": false, "listed_count": 382, "profile_background_tile": false, "lang": "en", "profile_background_image_url_https": "https://pbs.twimg.com/profile_background_images/378800000113803018/be332da092a8abf8661fe657f6427d2c.jpeg"}, "extended_tweet": {"display_text_range": [26, 299], "entities": {"user_mentions": [{"indices": [0, 13], "name": "ElizabethCMcLaughlin", "id_str": "335060282", "screen_name": "ECMcLaughlin", "id": 335060282}, {"indices": [14, 25], "name": "Dawn \ud83d\udc9c#Resist \ud83c\udf0a\ud83c\udf0a2018", "id_str": "1952510090", "screen_name": "dawnresist", "id": 1952510090}], "hashtags": [{"indices": [41, 48], "text": "Anthem"}, {"indices": [51, 58], "text": "Choice"}, {"indices": [59, 65], "text": "Women"}, {"indices": [66, 72], "text": "LGBTQ"}, {"indices": [73, 90], "text": "BlackLivesMatter"}, {"indices": [91, 96], "text": "STEM"}, {"indices": [97, 107], "text": "Democracy"}, {"indices": [170, 188], "text": "PlannedParenthood"}, {"indices": [189, 198], "text": "Dreamers"}, {"indices": [199, 207], "text": "climate"}, {"indices": [208, 222], "text": "WomensMarchLA"}, {"indices": [223, 230], "text": "Sexism"}, {"indices": [231, 242], "text": "Homophobia"}, {"indices": [243, 250], "text": "Racism"}, {"indices": [251, 257], "text": "MeToo"}, {"indices": [258, 266], "text": "TimesUp"}, {"indices": [267, 279], "text": "WomensMarch"}, {"indices": [281, 286], "text": "CHIP"}, {"indices": [287, 299], "text": "DreamActNow"}], "symbols": [], "urls": [{"display_url": "calililiindies.bandcamp.com/track/in-hard-\u2026", "indices": [114, 137], "url": "https://t.co/N7htMPDHzc", "expanded_url": "https://calililiindies.bandcamp.com/track/in-hard-times-anthem-4-choice-lgbtq-rights-civil-rights-climate-science-full-track-cali-lili-single-from-upcoming-debut-album-cali-lili-this-female-is-not-yet-rated-soundtrack-to-upcoming-feature"}, {"display_url": "twitter.com/thedavidcrosby\u2026", "indices": [142, 165], "url": "https://t.co/3CHghBbLUO", "expanded_url": "https://twitter.com/thedavidcrosby/status/882138869986086913"}]}, "full_text": "@ECMcLaughlin @dawnresist n Hard Times \u00a9 #Anthem 4 #Choice #Women #LGBTQ #BlackLivesMatter #STEM #Democracy \ud83c\udfc4\u200d\u2640\ufe0f  https://t.co/N7htMPDHzc \u2026   https://t.co/3CHghBbLUO \u2026   #PlannedParenthood #Dreamers #climate #WomensMarchLA #Sexism #Homophobia #Racism #MeToo #TimesUp #WomensMarch  #CHIP #DreamActNow"}, "favorite_count": 0, "id": 954541861988806656, "place": null, "is_quote_status": true, "truncated": true, "created_at": "Sat Jan 20 02:31:29 +0000 2018", "lang": "en", "source": "<a href=\"http://twitter.com\" rel=\"nofollow\">Twitter Web Client</a>", "filter_level": "low", "retweet_count": 1, "id_str": "954541861988806656", "quote_count": 0, "quoted_status": {"geo": null, "in_reply_to_user_id_str": null, "in_reply_to_screen_name": null, "text": "To all the songwriters \nWe need a really good one \n A We Shall Overcome , or an Ohio\nSomething", "user": {"following": null, "time_zone": null, "profile_image_url_https": "https://pbs.twimg.com/profile_images/1295576713/crosby1_normal.jpg", "contributors_enabled": false, "profile_link_color": "038543", "profile_sidebar_fill_color": "F6F6F6", "favourites_count": 74610, "default_profile": false, "description": "musician, singer, songwriter", "verified": true, "friends_count": 477, "is_translator": false, "id_str": "275361193", "profile_text_color": "333333", "created_at": "Fri Apr 01 03:49:09 +0000 2011", "followers_count": 101429, "notifications": null, "profile_banner_url": "https://pbs.twimg.com/profile_banners/275361193/1506690788", "profile_image_url": "http://pbs.twimg.com/profile_images/1295576713/crosby1_normal.jpg", "profile_background_image_url": "http://abs.twimg.com/images/themes/theme18/bg.gif", "protected": false, "geo_enabled": true, "profile_sidebar_border_color": "EEEEEE", "translator_type": "none", "id": 275361193, "statuses_count": 37150, "name": "David Crosby", "location": "California", "utc_offset": null, "profile_background_color": "ACDED6", "url": "https://ffm.to/skytrails", "screen_name": "thedavidcrosby", "profile_use_background_image": true, "follow_request_sent": null, "default_profile_image": false, "listed_count": 1044, "profile_background_tile": false, "lang": "en", "profile_background_image_url_https": "https://abs.twimg.com/images/themes/theme18/bg.gif"}, "favorite_count": 1275, "id": 882138869986086913, "place": null, "is_quote_status": false, "truncated": false, "created_at": "Tue Jul 04 07:27:50 +0000 2017", "source": "<a href=\"http://twitter.com/#!/download/ipad\" rel=\"nofollow\">Twitter for iPad</a>", "filter_level": "low", "retweet_count": 358, "id_str": "882138869986086913", "quote_count": 122, "reply_count": 177, "coordinates": null, "entities": {"user_mentions": [], "hashtags": [], "symbols": [], "urls": []}, "in_reply_to_user_id": null, "in_reply_to_status_id": null, "retweeted": false, "in_reply_to_status_id_str": null, "favorited": false, "contributors": null, "lang": "en"}, "coordinates": null, "entities": {"user_mentions": [{"indices": [0, 13], "name": "ElizabethCMcLaughlin", "id_str": "335060282", "screen_name": "ECMcLaughlin", "id": 335060282}, {"indices": [14, 25], "name": "Dawn \ud83d\udc9c#Resist \ud83c\udf0a\ud83c\udf0a2018", "id_str": "1952510090", "screen_name": "dawnresist", "id": 1952510090}], "hashtags": [{"indices": [41, 48], "text": "Anthem"}, {"indices": [51, 58], "text": "Choice"}, {"indices": [59, 65], "text": "Women"}, {"indices": [66, 72], "text": "LGBTQ"}, {"indices": [73, 90], "text": "BlackLivesMatter"}, {"indices": [91, 96], "text": "STEM"}, {"indices": [97, 107], "text": "Democracy"}], "symbols": [], "urls": [{"display_url": "twitter.com/i/web/status/9\u2026", "indices": [114, 137], "url": "https://t.co/AoRYYEPaqp", "expanded_url": "https://twitter.com/i/web/status/954541861988806656"}]}, "in_reply_to_user_id": 335060282, "in_reply_to_status_id": 954521579664310273, "retweeted": false, "in_reply_to_status_id_str": "954521579664310273", "favorited": false, "quoted_status_id": 882138869986086913, "contributors": null, "display_text_range": [26, 140], "text": "@ECMcLaughlin @dawnresist n Hard Times \u00a9 #Anthem 4 #Choice #Women #LGBTQ #BlackLivesMatter #STEM #Democracy \ud83c\udfc4\u200d\u2640\ufe0f\u2026 https://t.co/AoRYYEPaqp", "reply_count": 0, "possibly_sensitive": false}, "quote_count": 0, "quoted_status": {"geo": null, "in_reply_to_user_id_str": null, "in_reply_to_screen_name": null, "text": "To all the songwriters \nWe need a really good one \n A We Shall Overcome , or an Ohio\nSomething", "user": {"following": null, "time_zone": null, "profile_image_url_https": "https://pbs.twimg.com/profile_images/1295576713/crosby1_normal.jpg", "contributors_enabled": false, "profile_link_color": "038543", "profile_sidebar_fill_color": "F6F6F6", "favourites_count": 74610, "default_profile": false, "description": "musician, singer, songwriter", "verified": true, "friends_count": 477, "is_translator": false, "id_str": "275361193", "profile_text_color": "333333", "created_at": "Fri Apr 01 03:49:09 +0000 2011", "followers_count": 101429, "notifications": null, "profile_banner_url": "https://pbs.twimg.com/profile_banners/275361193/1506690788", "profile_image_url": "http://pbs.twimg.com/profile_images/1295576713/crosby1_normal.jpg", "profile_background_image_url": "http://abs.twimg.com/images/themes/theme18/bg.gif", "protected": false, "geo_enabled": true, "profile_sidebar_border_color": "EEEEEE", "translator_type": "none", "id": 275361193, "statuses_count": 37150, "name": "David Crosby", "location": "California", "utc_offset": null, "profile_background_color": "ACDED6", "url": "https://ffm.to/skytrails", "screen_name": "thedavidcrosby", "profile_use_background_image": true, "follow_request_sent": null, "default_profile_image": false, "listed_count": 1044, "profile_background_tile": false, "lang": "en", "profile_background_image_url_https": "https://abs.twimg.com/images/themes/theme18/bg.gif"}, "favorite_count": 1275, "id": 882138869986086913, "place": null, "is_quote_status": false, "truncated": false, "created_at": "Tue Jul 04 07:27:50 +0000 2017", "source": "<a href=\"http://twitter.com/#!/download/ipad\" rel=\"nofollow\">Twitter for iPad</a>", "filter_level": "low", "retweet_count": 358, "id_str": "882138869986086913", "quote_count": 122, "reply_count": 177, "coordinates": null, "entities": {"user_mentions": [], "hashtags": [], "symbols": [], "urls": []}, "in_reply_to_user_id": null, "in_reply_to_status_id": null, "retweeted": false, "in_reply_to_status_id_str": null, "favorited": false, "contributors": null, "lang": "en"}, "coordinates": null, "entities": {"user_mentions": [{"indices": [3, 18], "name": "CaliLili\u2122\ud83c\udf2c\ufe0f\ud83c\udf0a\ud83d\udc2c\ud83c\udf0a \ud83c\udf08\ud83c\udfc4\u200d\u2640\ufe0f\ud83c\udff3\ufe0f\u200d\ud83c\udf08\ud83d\udc9e\ud83d\ude0e\ud83e\udd19\ud83d\udd4a\ufe0f\ud83c\udf0d", "id_str": "594100783", "screen_name": "CaliLiliIndies", "id": 594100783}, {"indices": [20, 33], "name": "ElizabethCMcLaughlin", "id_str": "335060282", "screen_name": "ECMcLaughlin", "id": 335060282}, {"indices": [34, 45], "name": "Dawn \ud83d\udc9c#Resist \ud83c\udf0a\ud83c\udf0a2018", "id_str": "1952510090", "screen_name": "dawnresist", "id": 1952510090}], "hashtags": [{"indices": [61, 68], "text": "Anthem"}, {"indices": [71, 78], "text": "Choice"}, {"indices": [79, 85], "text": "Women"}, {"indices": [86, 92], "text": "LGBTQ"}, {"indices": [93, 110], "text": "BlackLivesMatter"}, {"indices": [111, 116], "text": "STEM"}, {"indices": [117, 127], "text": "Democracy"}], "symbols": [], "urls": []}, "in_reply_to_user_id": null, "in_reply_to_status_id": null, "retweeted": false, "timestamp_ms": "1516416102838", "in_reply_to_status_id_str": null, "favorited": false, "quoted_status_id": 882138869986086913, "contributors": null, "lang": "en", "reply_count": 0}