{"geo": null, "in_reply_to_user_id_str": null, "in_reply_to_screen_name": null, "quoted_status_id_str": "954536494131220483", "user": {"following": null, "time_zone": "Arizona", "profile_image_url_https": "https://pbs.twimg.com/profile_images/878798637257547777/zZB2c2Ob_normal.jpg", "contributors_enabled": false, "profile_link_color": "E81C4F", "profile_sidebar_fill_color": "DAECF4", "favourites_count": 38834, "default_profile": false, "description": "\u201dYou don\u2019t get rights if you don\u2019t fight for them.\u201c - Raul Esparza", "verified": false, "friends_count": 1795, "is_translator": false, "id_str": "20646356", "profile_text_color": "663B12", "created_at": "Thu Feb 12 01:39:12 +0000 2009", "followers_count": 776, "notifications": null, "profile_banner_url": "https://pbs.twimg.com/profile_banners/20646356/1516172303", "profile_image_url": "http://pbs.twimg.com/profile_images/878798637257547777/zZB2c2Ob_normal.jpg", "profile_background_image_url": "http://pbs.twimg.com/profile_background_images/569908264322617344/b7tFemaH.jpeg", "protected": false, "geo_enabled": true, "profile_sidebar_border_color": "C6E2EE", "translator_type": "none", "id": 20646356, "statuses_count": 28958, "name": "Professor Kath", "location": "New York", "utc_offset": -25200, "profile_background_color": "ABB8C2", "url": null, "screen_name": "grassysvu67", "profile_use_background_image": true, "follow_request_sent": null, "default_profile_image": false, "listed_count": 30, "profile_background_tile": true, "lang": "en", "profile_background_image_url_https": "https://pbs.twimg.com/profile_background_images/569908264322617344/b7tFemaH.jpeg"}, "favorite_count": 0, "id": 954536936630292480, "place": null, "is_quote_status": true, "truncated": false, "created_at": "Sat Jan 20 02:11:54 +0000 2018", "lang": "en", "source": "<a href=\"http://twitter.com/download/iphone\" rel=\"nofollow\">Twitter for iPhone</a>", "filter_level": "low", "retweet_count": 0, "smapp_timestamp": "Fri Jan 19 21:11:55 +0000 2018", "id_str": "954536936630292480", "quote_count": 0, "quoted_status": {"geo": null, "in_reply_to_user_id_str": null, "in_reply_to_screen_name": null, "text": ".@Halsey to speak at the 2018 #WomensMarch in NYC https://t.co/tdPqZmd3NZ", "user": {"following": null, "time_zone": "Eastern Time (US & Canada)", "profile_image_url_https": "https://pbs.twimg.com/profile_images/876878315256250369/Zkusf5bc_normal.jpg", "contributors_enabled": false, "profile_link_color": "1EB0E8", "profile_sidebar_fill_color": "CCCCCC", "favourites_count": 5869, "default_profile": false, "description": "music \u2022 charts \u2022 news \u2022 more | @billboarddance \u2022 @billboardhiphop \u2022 @billboardlatin \u2022 @hot100fest | tweets by @miraoliviaa", "verified": true, "friends_count": 3138, "is_translator": false, "id_str": "9695312", "profile_text_color": "333333", "created_at": "Thu Oct 25 21:33:23 +0000 2007", "followers_count": 6236229, "notifications": null, "profile_banner_url": "https://pbs.twimg.com/profile_banners/9695312/1516374818", "profile_image_url": "http://pbs.twimg.com/profile_images/876878315256250369/Zkusf5bc_normal.jpg", "profile_background_image_url": "http://pbs.twimg.com/profile_background_images/859213624/0a4c4debd18292678c5c55a64c9fd228.png", "protected": false, "geo_enabled": true, "profile_sidebar_border_color": "FFFFFF", "translator_type": "regular", "id": 9695312, "statuses_count": 168743, "name": "billboard", "location": "Worldwide!", "utc_offset": -18000, "profile_background_color": "FFFFFF", "url": "http://billboard.com", "screen_name": "billboard", "profile_use_background_image": false, "follow_request_sent": null, "default_profile_image": false, "listed_count": 22045, "profile_background_tile": false, "lang": "en", "profile_background_image_url_https": "https://pbs.twimg.com/profile_background_images/859213624/0a4c4debd18292678c5c55a64c9fd228.png"}, "favorite_count": 456, "id": 954536494131220483, "place": null, "is_quote_status": false, "truncated": false, "created_at": "Sat Jan 20 02:10:09 +0000 2018", "source": "<a href=\"http://www.socialflow.com\" rel=\"nofollow\">SocialFlow</a>", "filter_level": "low", "retweet_count": 143, "id_str": "954536494131220483", "quote_count": 2, "reply_count": 8, "coordinates": null, "entities": {"user_mentions": [{"indices": [1, 8], "name": "h", "id_str": "45709328", "screen_name": "halsey", "id": 45709328}], "hashtags": [{"indices": [30, 42], "text": "WomensMarch"}], "symbols": [], "urls": [{"display_url": "blbrd.cm/LbSX77", "indices": [50, 73], "url": "https://t.co/tdPqZmd3NZ", "expanded_url": "http://blbrd.cm/LbSX77"}]}, "in_reply_to_user_id": null, "in_reply_to_status_id": null, "retweeted": false, "in_reply_to_status_id_str": null, "favorited": false, "contributors": null, "lang": "en", "possibly_sensitive": false}, "coordinates": null, "entities": {"user_mentions": [], "hashtags": [], "symbols": [], "urls": [{"display_url": "twitter.com/billboard/stat\u2026", "indices": [29, 52], "url": "https://t.co/LGozVIT5vH", "expanded_url": "https://twitter.com/billboard/status/954536494131220483"}]}, "in_reply_to_user_id": null, "in_reply_to_status_id": null, "retweeted": false, "timestamp_ms": "1516414314788", "in_reply_to_status_id_str": null, "favorited": false, "quoted_status_id": 954536494131220483, "contributors": null, "display_text_range": [0, 28], "text": "This is going to be amazing! https://t.co/LGozVIT5vH", "reply_count": 0, "possibly_sensitive": false}