{"source": "<a href=\"http://twitter.com\" rel=\"nofollow\">Twitter Web Client</a>", "retweet_count": 0, "in_reply_to_status_id": 954487381352042497, "in_reply_to_user_id_str": "872850193678450689", "in_reply_to_user_id": 872850193678450689, "place": null, "timestamp_ms": "1516402649246", "lang": "en", "text": "@SisDistrictOR3 @IndivisibleTeam @swingleft @flippable_org @Morning_Joe Awesome! Excited that your are attending.\u2026 https://t.co/rt3Bns0ko1", "in_reply_to_screen_name": "SisDistrictOR3", "reply_count": 0, "id_str": "954488007800758272", "quote_count": 0, "geo": null, "contributors": null, "display_text_range": [72, 140], "truncated": true, "user": {"profile_sidebar_border_color": "C0DEED", "is_translator": false, "verified": false, "favourites_count": 2540, "contributors_enabled": false, "profile_image_url_https": "https://pbs.twimg.com/profile_images/825554817166766081/IyPwsFX5_normal.jpg", "profile_background_color": "F5F8FA", "profile_link_color": "1DA1F2", "translator_type": "none", "url": "http://www.sisterdistrict.com", "profile_background_image_url": "", "profile_background_image_url_https": "", "statuses_count": 1709, "followers_count": 11399, "screen_name": "Sister_District", "profile_text_color": "333333", "friends_count": 889, "geo_enabled": true, "default_profile_image": false, "default_profile": true, "notifications": null, "profile_image_url": "http://pbs.twimg.com/profile_images/825554817166766081/IyPwsFX5_normal.jpg", "profile_use_background_image": true, "id_str": "818646699023290368", "lang": "en", "time_zone": "Pacific Time (US & Canada)", "name": "Sister District", "location": "San Francisco, CA", "id": 818646699023290368, "created_at": "Tue Jan 10 02:32:37 +0000 2017", "profile_sidebar_fill_color": "DDEEF6", "listed_count": 138, "follow_request_sent": null, "profile_banner_url": "https://pbs.twimg.com/profile_banners/818646699023290368/1510295836", "profile_background_tile": false, "following": null, "description": "We match blue volunteers with swing districts to get Dems elected nationwide. Join us to support state races now! #RedToBlue #BlueWave  http://bit.ly/2AmG9oW", "protected": false, "utc_offset": -28800}, "id": 954488007800758272, "created_at": "Fri Jan 19 22:57:29 +0000 2018", "is_quote_status": false, "retweeted": false, "coordinates": null, "favorite_count": 0, "extended_tweet": {"entities": {"urls": [], "user_mentions": [{"name": "Sister_DistrictOR-3", "indices": [0, 15], "id": 872850193678450689, "screen_name": "SisDistrictOR3", "id_str": "872850193678450689"}, {"name": "Indivisible Guide", "indices": [16, 32], "id": 810590628727914496, "screen_name": "IndivisibleTeam", "id_str": "810590628727914496"}, {"name": "Swing Left", "indices": [33, 43], "id": 800704496246484992, "screen_name": "swingleft", "id_str": "800704496246484992"}, {"name": "Flippable", "indices": [44, 58], "id": 798729566126829568, "screen_name": "flippable_org", "id_str": "798729566126829568"}, {"name": "Morning Joe", "indices": [59, 71], "id": 254117355, "screen_name": "Morning_Joe", "id_str": "254117355"}], "hashtags": [{"indices": [114, 132], "text": "MarchesToMeetings"}, {"indices": [133, 142], "text": "BlueWave"}, {"indices": [143, 155], "text": "WomensMarch"}], "symbols": []}, "full_text": "@SisDistrictOR3 @IndivisibleTeam @swingleft @flippable_org @Morning_Joe Awesome! Excited that your are attending. #MarchesToMeetings #BlueWave #WomensMarch", "display_text_range": [72, 155]}, "entities": {"urls": [{"url": "https://t.co/rt3Bns0ko1", "indices": [115, 138], "expanded_url": "https://twitter.com/i/web/status/954488007800758272", "display_url": "twitter.com/i/web/status/9\u2026"}], "user_mentions": [{"name": "Sister_DistrictOR-3", "indices": [0, 15], "id": 872850193678450689, "screen_name": "SisDistrictOR3", "id_str": "872850193678450689"}, {"name": "Indivisible Guide", "indices": [16, 32], "id": 810590628727914496, "screen_name": "IndivisibleTeam", "id_str": "810590628727914496"}, {"name": "Swing Left", "indices": [33, 43], "id": 800704496246484992, "screen_name": "swingleft", "id_str": "800704496246484992"}, {"name": "Flippable", "indices": [44, 58], "id": 798729566126829568, "screen_name": "flippable_org", "id_str": "798729566126829568"}, {"name": "Morning Joe", "indices": [59, 71], "id": 254117355, "screen_name": "Morning_Joe", "id_str": "254117355"}], "hashtags": [], "symbols": []}, "filter_level": "low", "smapp_timestamp": "Fri Jan 19 17:57:29 +0000 2018", "in_reply_to_status_id_str": "954487381352042497", "favorited": false}