{"reply_count": 0, "text": "This was a nice welcome on this frigid AF morning! \ud83d\ude0aThx! \n#FollowBackResistance \n#FBR \n#WomensMarch2018 https://t.co/6udr6d38hI", "lang": "en", "quoted_status_id": 954314446297497600, "favorite_count": 0, "retweeted": false, "in_reply_to_screen_name": null, "id": 954391899808436224, "in_reply_to_status_id_str": null, "created_at": "Fri Jan 19 16:35:35 +0000 2018", "place": null, "coordinates": null, "in_reply_to_user_id_str": null, "in_reply_to_user_id": null, "favorited": false, "possibly_sensitive": false, "retweet_count": 0, "quote_count": 0, "smapp_timestamp": "Fri Jan 19 11:35:35 +0000 2018", "id_str": "954391899808436224", "geo": null, "contributors": null, "source": "<a href=\"http://twitter.com/download/iphone\" rel=\"nofollow\">Twitter for iPhone</a>", "filter_level": "low", "user": {"location": "NY, NY", "statuses_count": 8304, "following": null, "default_profile": false, "followers_count": 758, "profile_image_url": "http://pbs.twimg.com/profile_images/865147810575917057/aP_GRqgk_normal.jpg", "url": null, "utc_offset": -21600, "profile_background_tile": true, "profile_image_url_https": "https://pbs.twimg.com/profile_images/865147810575917057/aP_GRqgk_normal.jpg", "id": 88679204, "profile_link_color": "088253", "created_at": "Mon Nov 09 14:48:22 +0000 2009", "protected": false, "is_translator": false, "profile_background_color": "EDECE9", "profile_banner_url": "https://pbs.twimg.com/profile_banners/88679204/1495102165", "contributors_enabled": false, "name": "GneissGirl 94% \ud83d\udcaa\ud83c\udffe", "profile_sidebar_fill_color": "E3E2DE", "verified": false, "profile_background_image_url": "http://pbs.twimg.com/profile_background_images/52317947/DSCI0127.JPG", "translator_type": "none", "description": "Adorable, fit, witty black woman. True Democrat. Spirit Animal: Dragon \ud83d\udc09 Stylishly Opinionated. All Liberal/non-Berniecrat \u2018Jodi\u2019s\u2019 = Follow", "friends_count": 1003, "geo_enabled": false, "profile_sidebar_border_color": "D3D2CF", "id_str": "88679204", "profile_use_background_image": true, "time_zone": "Central Time (US & Canada)", "default_profile_image": false, "listed_count": 0, "profile_text_color": "634047", "follow_request_sent": null, "lang": "en", "profile_background_image_url_https": "https://pbs.twimg.com/profile_background_images/52317947/DSCI0127.JPG", "favourites_count": 45032, "notifications": null, "screen_name": "GniessGirl"}, "in_reply_to_status_id": null, "timestamp_ms": "1516379735315", "quoted_status_id_str": "954314446297497600", "truncated": false, "entities": {"hashtags": [{"text": "FollowBackResistance", "indices": [58, 79]}, {"text": "FBR", "indices": [81, 85]}, {"text": "WomensMarch2018", "indices": [87, 103]}], "symbols": [], "urls": [{"display_url": "twitter.com/tuttlentexas/s\u2026", "indices": [104, 127], "url": "https://t.co/6udr6d38hI", "expanded_url": "https://twitter.com/tuttlentexas/status/954314446297497600"}], "user_mentions": []}, "quoted_status": {"reply_count": 7, "text": "Happy #ff to my new twitter buddies! @aa_tweeter @HelenResists @cdjinteriors @GniessGirl @D4thewin @AJBC143\u2026 https://t.co/PATrnaEbua", "lang": "en", "favorite_count": 9, "retweeted": false, "in_reply_to_screen_name": null, "id": 954314446297497600, "in_reply_to_status_id_str": null, "created_at": "Fri Jan 19 11:27:48 +0000 2018", "place": null, "coordinates": null, "in_reply_to_user_id_str": null, "in_reply_to_user_id": null, "extended_tweet": {"full_text": "Happy #ff to my new twitter buddies! @aa_tweeter @HelenResists @cdjinteriors @GniessGirl @D4thewin @AJBC143 @DumondKd @Selena_Adera @Frylikeanegg @skipbolden\n@PresidentMrEd \n@NeighborNerdy\n@ManicTVAddict", "display_text_range": [0, 203], "entities": {"hashtags": [{"text": "ff", "indices": [6, 9]}], "symbols": [], "urls": [], "user_mentions": [{"name": "\u2227  \u0e04 \u044f \u2202 \u03b9 \u03b7 \u2240\u2243 \ud83c\udf10", "screen_name": "aa_tweeter", "indices": [37, 48], "id": 3973087414, "id_str": "3973087414"}, {"name": "Helen Resists", "screen_name": "HelenResists", "indices": [49, 62], "id": 2310662821, "id_str": "2310662821"}, {"name": "Marielle   #PatriotsResist", "screen_name": "cdjinteriors", "indices": [63, 76], "id": 2347282453, "id_str": "2347282453"}, {"name": "GneissGirl 94% \ud83d\udcaa\ud83c\udffe", "screen_name": "GniessGirl", "indices": [77, 88], "id": 88679204, "id_str": "88679204"}, {"name": "Pix303", "screen_name": "D4thewin", "indices": [89, 98], "id": 806032591203762176, "id_str": "806032591203762176"}, {"name": "Stop Trump!!!", "screen_name": "AJBC143", "indices": [99, 107], "id": 242890984, "id_str": "242890984"}, {"name": "kd", "screen_name": "DumondKd", "indices": [108, 117], "id": 637184320, "id_str": "637184320"}, {"name": "Selena Adera \ud83c\udf69", "screen_name": "Selena_Adera", "indices": [118, 131], "id": 839188838593540097, "id_str": "839188838593540097"}, {"name": "Laurie Fry", "screen_name": "Frylikeanegg", "indices": [132, 145], "id": 80466390, "id_str": "80466390"}, {"name": "Skip Bolden", "screen_name": "skipbolden", "indices": [146, 157], "id": 257265441, "id_str": "257265441"}, {"name": "President Mr. Ed", "screen_name": "PresidentMrEd", "indices": [158, 172], "id": 822526056, "id_str": "822526056"}, {"name": "N N W", "screen_name": "NeighborNerdy", "indices": [174, 188], "id": 864640541157281792, "id_str": "864640541157281792"}, {"name": "Jacob Thomas", "screen_name": "ManicTVAddict", "indices": [189, 203], "id": 929544088730394624, "id_str": "929544088730394624"}]}}, "retweet_count": 3, "quote_count": 0, "id_str": "954314446297497600", "geo": null, "contributors": null, "source": "<a href=\"http://twitter.com\" rel=\"nofollow\">Twitter Web Client</a>", "filter_level": "low", "user": {"location": "Houston, TX", "statuses_count": 44365, "following": null, "default_profile": true, "followers_count": 6490, "profile_image_url": "http://pbs.twimg.com/profile_images/952543604030894081/exPGeoO4_normal.jpg", "url": null, "utc_offset": -21600, "profile_background_tile": false, "profile_image_url_https": "https://pbs.twimg.com/profile_images/952543604030894081/exPGeoO4_normal.jpg", "id": 581436283, "profile_link_color": "1DA1F2", "created_at": "Wed May 16 02:07:46 +0000 2012", "protected": false, "is_translator": false, "profile_background_color": "C0DEED", "profile_banner_url": "https://pbs.twimg.com/profile_banners/581436283/1488853060", "contributors_enabled": false, "name": "Tuttle N. Texas", "profile_sidebar_fill_color": "DDEEF6", "verified": false, "profile_background_image_url": "http://abs.twimg.com/images/themes/theme1/bg.png", "translator_type": "none", "description": "The PROFANE shop steward, amateur speller, & would-be writer. #Union #LGBTQ #BlackLIvesMatter #Femenist #TheResistance oh #StarWars & #Cats too.", "friends_count": 6116, "geo_enabled": false, "profile_sidebar_border_color": "C0DEED", "id_str": "581436283", "profile_use_background_image": true, "time_zone": "Central Time (US & Canada)", "default_profile_image": false, "listed_count": 133, "profile_text_color": "333333", "follow_request_sent": null, "lang": "en", "profile_background_image_url_https": "https://abs.twimg.com/images/themes/theme1/bg.png", "favourites_count": 23494, "notifications": null, "screen_name": "TuttleNTexas"}, "in_reply_to_status_id": null, "favorited": false, "truncated": true, "entities": {"hashtags": [{"text": "ff", "indices": [6, 9]}], "symbols": [], "urls": [{"display_url": "twitter.com/i/web/status/9\u2026", "indices": [109, 132], "url": "https://t.co/PATrnaEbua", "expanded_url": "https://twitter.com/i/web/status/954314446297497600"}], "user_mentions": [{"name": "\u2227  \u0e04 \u044f \u2202 \u03b9 \u03b7 \u2240\u2243 \ud83c\udf10", "screen_name": "aa_tweeter", "indices": [37, 48], "id": 3973087414, "id_str": "3973087414"}, {"name": "Helen Resists", "screen_name": "HelenResists", "indices": [49, 62], "id": 2310662821, "id_str": "2310662821"}, {"name": "Marielle   #PatriotsResist", "screen_name": "cdjinteriors", "indices": [63, 76], "id": 2347282453, "id_str": "2347282453"}, {"name": "GneissGirl 94% \ud83d\udcaa\ud83c\udffe", "screen_name": "GniessGirl", "indices": [77, 88], "id": 88679204, "id_str": "88679204"}, {"name": "Pix303", "screen_name": "D4thewin", "indices": [89, 98], "id": 806032591203762176, "id_str": "806032591203762176"}, {"name": "Stop Trump!!!", "screen_name": "AJBC143", "indices": [99, 107], "id": 242890984, "id_str": "242890984"}]}, "is_quote_status": false}, "display_text_range": [0, 103], "is_quote_status": true}