{"possibly_sensitive": false, "smapp_timestamp": "Fri Jan 19 15:01:07 +0000 2018", "quoted_status_id": 954442174275387393, "in_reply_to_status_id_str": "954355926470930434", "filter_level": "low", "contributors": null, "id_str": "954443621440385024", "entities": {"hashtags": [], "symbols": [], "urls": [{"expanded_url": "https://twitter.com/wtfisgoingondon/status/954442174275387393", "display_url": "twitter.com/wtfisgoingondo\u2026", "url": "https://t.co/jX4m4bodL7", "indices": [16, 39]}], "user_mentions": [{"screen_name": "DonaldJTrumpJr", "id": 39344374, "indices": [0, 15], "id_str": "39344374", "name": "Donald Trump Jr."}]}, "display_text_range": [16, 39], "in_reply_to_status_id": 954355926470930434, "reply_count": 0, "geo": null, "coordinates": null, "text": "@DonaldJTrumpJr https://t.co/jX4m4bodL7", "in_reply_to_screen_name": "DonaldJTrumpJr", "timestamp_ms": "1516392066713", "favorite_count": 0, "quoted_status_id_str": "954442174275387393", "quoted_status": {"possibly_sensitive": false, "in_reply_to_status_id_str": null, "favorited": false, "contributors": null, "id_str": "954442174275387393", "entities": {"hashtags": [{"text": "memo", "indices": [0, 5]}, {"text": "FusionGPS", "indices": [6, 16]}, {"text": "FusionGPSTranscripts", "indices": [17, 38]}, {"text": "fusion", "indices": [39, 46]}, {"text": "transcriptiontuesday", "indices": [47, 68]}, {"text": "transcripts", "indices": [69, 81]}, {"text": "humor", "indices": [82, 88]}, {"text": "resist", "indices": [89, 96]}, {"text": "funny", "indices": [97, 103]}], "symbols": [], "urls": [{"expanded_url": "https://twitter.com/i/web/status/954442174275387393", "display_url": "twitter.com/i/web/status/9\u2026", "url": "https://t.co/1cCO50YWVl", "indices": [105, 128]}], "user_mentions": []}, "display_text_range": [0, 140], "in_reply_to_status_id": null, "reply_count": 1, "geo": null, "coordinates": null, "text": "#memo #FusionGPS #FusionGPSTranscripts #fusion #transcriptiontuesday #transcripts #humor #resist #funny\u2026 https://t.co/1cCO50YWVl", "in_reply_to_screen_name": null, "favorite_count": 6, "created_at": "Fri Jan 19 19:55:21 +0000 2018", "source": "<a href=\"http://twitter.com\" rel=\"nofollow\">Twitter Web Client</a>", "user": {"follow_request_sent": null, "profile_banner_url": "https://pbs.twimg.com/profile_banners/11101742/1486477271", "location": "18073", "friends_count": 4482, "protected": false, "default_profile_image": false, "id_str": "11101742", "profile_background_image_url": "http://abs.twimg.com/images/themes/theme1/bg.png", "is_translator": false, "translator_type": "none", "notifications": null, "followers_count": 7930, "profile_background_color": "000000", "name": "Don't Leave Blank", "geo_enabled": false, "profile_use_background_image": false, "utc_offset": -21600, "profile_sidebar_fill_color": "000000", "following": null, "profile_sidebar_border_color": "000000", "created_at": "Wed Dec 12 20:23:57 +0000 2007", "default_profile": false, "verified": false, "statuses_count": 14469, "profile_text_color": "000000", "id": 11101742, "profile_background_image_url_https": "https://abs.twimg.com/images/themes/theme1/bg.png", "description": "Anti-Trump - I like 2 make light of things 2 brighten up a dark world.#antitrump #resist #resisttrump #uniteblue #funny #humor #satire #resistance", "contributors_enabled": false, "profile_image_url": "http://pbs.twimg.com/profile_images/847076405364084737/m0y16B1i_normal.jpg", "screen_name": "WTFisGoingOnDon", "listed_count": 39, "profile_image_url_https": "https://pbs.twimg.com/profile_images/847076405364084737/m0y16B1i_normal.jpg", "profile_link_color": "FAB81E", "profile_background_tile": false, "url": null, "time_zone": "Central Time (US & Canada)", "favourites_count": 17528, "lang": "en"}, "is_quote_status": false, "id": 954442174275387393, "extended_tweet": {"extended_entities": {"media": [{"expanded_url": "https://twitter.com/WTFisGoingOnDon/status/954442174275387393/photo/1", "indices": [132, 155], "media_url_https": "https://pbs.twimg.com/media/DT7bwowWAAAFGEy.jpg", "url": "https://t.co/nO7Yva0KIZ", "id": 954441799669514240, "display_url": "pic.twitter.com/nO7Yva0KIZ", "media_url": "http://pbs.twimg.com/media/DT7bwowWAAAFGEy.jpg", "id_str": "954441799669514240", "type": "photo", "sizes": {"medium": {"w": 792, "h": 454, "resize": "fit"}, "large": {"w": 792, "h": 454, "resize": "fit"}, "small": {"w": 680, "h": 390, "resize": "fit"}, "thumb": {"w": 150, "h": 150, "resize": "crop"}}}]}, "full_text": "#memo #FusionGPS #FusionGPSTranscripts #fusion #transcriptiontuesday #transcripts #humor #resist #funny #ResistTrump #TheResistance https://t.co/nO7Yva0KIZ", "entities": {"media": [{"expanded_url": "https://twitter.com/WTFisGoingOnDon/status/954442174275387393/photo/1", "indices": [132, 155], "media_url_https": "https://pbs.twimg.com/media/DT7bwowWAAAFGEy.jpg", "url": "https://t.co/nO7Yva0KIZ", "id": 954441799669514240, "display_url": "pic.twitter.com/nO7Yva0KIZ", "media_url": "http://pbs.twimg.com/media/DT7bwowWAAAFGEy.jpg", "id_str": "954441799669514240", "type": "photo", "sizes": {"medium": {"w": 792, "h": 454, "resize": "fit"}, "large": {"w": 792, "h": 454, "resize": "fit"}, "small": {"w": 680, "h": 390, "resize": "fit"}, "thumb": {"w": 150, "h": 150, "resize": "crop"}}}], "hashtags": [{"text": "memo", "indices": [0, 5]}, {"text": "FusionGPS", "indices": [6, 16]}, {"text": "FusionGPSTranscripts", "indices": [17, 38]}, {"text": "fusion", "indices": [39, 46]}, {"text": "transcriptiontuesday", "indices": [47, 68]}, {"text": "transcripts", "indices": [69, 81]}, {"text": "humor", "indices": [82, 88]}, {"text": "resist", "indices": [89, 96]}, {"text": "funny", "indices": [97, 103]}, {"text": "ResistTrump", "indices": [104, 116]}, {"text": "TheResistance", "indices": [117, 131]}], "symbols": [], "urls": [], "user_mentions": []}, "display_text_range": [0, 131]}, "place": null, "truncated": true, "in_reply_to_user_id_str": null, "lang": "und", "in_reply_to_user_id": null, "filter_level": "low", "retweeted": false, "retweet_count": 3, "quote_count": 1}, "created_at": "Fri Jan 19 20:01:06 +0000 2018", "source": "<a href=\"http://twitter.com/#!/download/ipad\" rel=\"nofollow\">Twitter for iPad</a>", "user": {"follow_request_sent": null, "profile_banner_url": "https://pbs.twimg.com/profile_banners/979213272/1500600226", "location": "#TheResistance", "friends_count": 2808, "protected": false, "default_profile_image": false, "id_str": "979213272", "profile_background_image_url": "http://abs.twimg.com/images/themes/theme1/bg.png", "is_translator": false, "translator_type": "none", "notifications": null, "followers_count": 1478, "profile_background_color": "000000", "name": "\ud83c\udf0asweetleaf\ud83c\udf0a (aka very stable genius)", "geo_enabled": true, "profile_use_background_image": false, "utc_offset": -18000, "profile_sidebar_fill_color": "000000", "following": null, "profile_sidebar_border_color": "000000", "created_at": "Thu Nov 29 21:47:08 +0000 2012", "default_profile": false, "verified": false, "statuses_count": 27562, "profile_text_color": "000000", "id": 979213272, "profile_background_image_url_https": "https://abs.twimg.com/images/themes/theme1/bg.png", "description": "If you are a \"deplorable\", go jump off a bridge. #Idiocracy is happening now. Nazi's & Trump supporters will be blocked. I only believe in @TheGoodGodAbove", "contributors_enabled": false, "profile_image_url": "http://pbs.twimg.com/profile_images/881951314833534976/03H2n7LB_normal.jpg", "screen_name": "great_sweetleaf", "listed_count": 1, "profile_image_url_https": "https://pbs.twimg.com/profile_images/881951314833534976/03H2n7LB_normal.jpg", "profile_link_color": "981CEB", "profile_background_tile": false, "url": "http://www.TrumpIsASexPredator.com", "time_zone": "Eastern Time (US & Canada)", "favourites_count": 77809, "lang": "en"}, "is_quote_status": true, "id": 954443621440385024, "favorited": false, "place": null, "truncated": false, "in_reply_to_user_id_str": "39344374", "lang": "und", "in_reply_to_user_id": 39344374, "retweeted": false, "retweet_count": 0, "quote_count": 0}